Workbook

Sheet Customers
A1: Customer_ID | B1: FirstName | C1: LastName | D1: Customer_Name | E1: Gender | F1: BirthDate | G1: City | H1: JoinDate
A2: C001 | B2: Michael | C2: Davis | D2: =CONCATENATE(B2," ",C2) -> Michael Davis | E2: Male | F2: 35319 | G2: Osborneport | H2: 44829
A3: C002 | B3: Michael | C3: Miller | D3: =CONCATENATE(B3," ",C3) -> Michael Miller | E3: Male | F3: 21780 | G3: New Gabrielleport | H3: 44138
A4: C003 | B4: Carol | C4: Hays | D4: =CONCATENATE(B4," ",C4) -> Carol Hays | E4: Female | F4: 38461 | G4: Port Allen | H4: 45334
A5: C004 | B5: Joseph | C5: Ward | D5: =CONCATENATE(B5," ",C5) -> Joseph Ward | E5: Male | F5: 33771 | G5: East Edgarborough | H5: 45544
A6: C005 | B6: Jamie | C6: Salinas | D6: =CONCATENATE(B6," ",C6) -> Jamie Salinas | E6: Male | F6: 33773 | G6: Port Kimberly | H6: 44616
A7: C006 | B7: Danny | C7: Moore | D7: =CONCATENATE(B7," ",C7) -> Danny Moore | E7: Male | F7: 31688 | G7: Costaberg | H7: 44751
A8: C007 | B8: Erin | C8: Walker | D8: =CONCATENATE(B8," ",C8) -> Erin Walker | E8: Male | F8: 31058 | G8: West Jasmine | H8: 44482
A9: C008 | B9: Isaiah | C9: Williams | D9: =CONCATENATE(B9," ",C9) -> Isaiah Williams | E9: Male | F9: 22233 | G9: New Michaelland | H9: 45720
A10: C009 | B10: Richard | C10: Pacheco | D10: =CONCATENATE(B10," ",C10) -> Richard Pacheco | E10: Female | F10: 38214 | G10: West Lisaville | H10: 45764
A11: C010 | B11: Catherine | C11: Rice | D11: =CONCATENATE(B11," ",C11) -> Catherine Rice | E11: Male | F11: 28106 | G11: West Carol | H11: 45861
A12: C011 | B12: Haley | C12: Williams | D12: =CONCATENATE(B12," ",C12) -> Haley Williams | E12: Male | F12: 35492 | G12: Leburgh | H12: 45058
A13: C012 | B13: Dale | C13: Perry | D13: =CONCATENATE(B13," ",C13) -> Dale Perry | E13: Male | F13: 32850 | G13: Lake Dawn | H13: 44393
... A201: C200 | B201: Ronald | C201: Haley | D201: =CONCATENATE(B201," ",C201) -> Ronald Haley | E201: Male | F201: 37249 | G201: Jenniferbury | H201: 45832

Sheet Products
A1: ProductID | B1: ProductName | C1: Category | D1: SubCategory | E1: Unite_Price | F1: Cost_Price
A2: P001 | B2: Like Camera | C2: Electronics | D2: Camera | E2: 1673.69 | F2: 1323.38
A3: P002 | B3: Audience Television | C3: Electronics | D3: Television | E3: 818.76 | F3: 527.62
A4: P003 | B4: Here Footwear | C4: Fashion | D4: Footwear | E4: 1102.7918 | F4: 169.03
A5: P004 | B5: Four Accessories | C5: Fashion | D5: Accessories | E5: 1853.77 | F5: 1363.52
A6: P005 | B6: Knowledge Bags | C6: Fashion | D6: Bags | E6: 1396.22 | F6: 1004.09
A7: P006 | B7: Company Fruits | C7: Groceries | D7: Fruits | E7: 318.05 | F7: 742.26522
A8: P007 | B8: Understand Camera | C8: Electronics | D8: Camera | E8: 1474.12 | F8: 764.02
A9: P008 | B9: Recognize Footwear | C9: Fashion | D9: Footwear | E9: 109.78 | F9: 70.59
A10: P009 | B10: Us Snacks | C10: Groceries | D10: Snacks | E10: 123.19 | F10: 80.36
A11: P010 | B11: Step Smartphone | C11: Electronics | D11: Smartphone | E11: 1194.12 | F11: 838.95
A12: P011 | B12: Either Headphones | C12: Electronics | D12: Headphones | E12: 248.57 | F12: 190.67
A13: P012 | B13: Above Camera | C13: Electronics | D13: Camera | E13: 1193.09 | F13: 818.24
... A51: P050 | B51: Maybe Footwear | C51: Fashion | D51: Footwear | E51: 1044.64 | F51: 775.07

Sheet Stores
A1: StoreID | B1: StoreName | C1: City | D1: Region
A2: S001 | B2: MegaMart Jimenezborough | C2: Jimenezborough | D2: South
A3: S002 | B3: MegaMart Peckmouth | C3: Peckmouth | D3: East
A4: S003 | B4: MegaMart New Michele | C4: New Michele | D4: West
A5: S004 | B5: MegaMart Brianahaven | C5: Brianahaven | D5: North
A6: S005 | B6: MegaMart Johnmouth | C6: Johnmouth | D6: East

Sheet Transactions
A1: TransactionID | B1: Date | C1: CustomerID | D1: Customer_Name | E1: Gender | F1: Birth_Date | G1: City | H1: Join_Date | I1: ProductID | J1: Product_Name | K1: Category | L1: Sub_Category | M1: Unite_Price | N1: Cost_Price | O1: StoreID | P1: Store Name | Q1: Region | R1: Quantity | S1: Discount | T1: PaymentMethod | U1: Sales Amount | V1: Total Cost Price | W1: Profit
A2: T00303 | B2: 45179 | C2: C013 | D2: =VLOOKUP(C2,Customers!$A$1:$H$201,4,0) -> Robert Anderson | E2: =VLOOKUP(C2,Customers!$A$1:$H$201,5,0) -> Male | F2: =VLOOKUP(C2,Customers!$A$1:$H$201,6,0) -> 20117 | G2: =VLOOKUP(C2,Customers!$A$1:$H$201,7,0) -> Jillianhaven | H2: =VLOOKUP(C2,Customers!$A$1:$H$201,8,0) -> 45007 | I2: P017 | J2: =VLOOKUP(I2,Products!$A$1:$F$51,2,0) -> Find Headphones | K2: =VLOOKUP(I2,Products!$A$1:$F$51,3,0) -> Electronics | L2: =VLOOKUP(I2,Products!$A$1:$F$51,4,0) -> Headphones | M2: =VLOOKUP(I2,Products!$A$1:$F$51,5,0) -> 1246.11 | N2: =VLOOKUP(I2,Products!$A$1:$F$51,6,0) -> 833.52 | O2: S003 | P2: =VLOOKUP(O2,Stores!$A$1:$D$6,2,0) -> MegaMart New Michele | Q2: =VLOOKUP(O2,Stores!$A$1:$D$6,4,0) -> West | R2: 4 | S2: 0.15 | T2: Bank Transfer | U2: =M2*R2 -> 4984.44 | V2: =N2*R2 -> 3334.08 | W2: =U2-V2-(1-S2) -> 1649.51
A3: T01769 | B3: 45179 | C3: C066 | D3: =VLOOKUP(C3,Customers!$A$1:$H$201,4,0) -> Jason Jenkins | E3: =VLOOKUP(C3,Customers!$A$1:$H$201,5,0) -> Female | F3: =VLOOKUP(C3,Customers!$A$1:$H$201,6,0) -> 31304 | G3: =VLOOKUP(C3,Customers!$A$1:$H$201,7,0) -> New Randychester | H3: =VLOOKUP(C3,Customers!$A$1:$H$201,8,0) -> 44186 | I3: P022 | J3: =VLOOKUP(I3,Products!$A$1:$F$51,2,0) -> How Vegetables | K3: =VLOOKUP(I3,Products!$A$1:$F$51,3,0) -> Groceries | L3: =VLOOKUP(I3,Products!$A$1:$F$51,4,0) -> Vegetables | M3: =VLOOKUP(I3,Products!$A$1:$F$51,5,0) -> 25.57 | N3: =VLOOKUP(I3,Products!$A$1:$F$51,6,0) -> 19.05 | O3: S004 | P3: =VLOOKUP(O3,Stores!$A$1:$D$6,2,0) -> MegaMart Brianahaven | Q3: =VLOOKUP(O3,Stores!$A$1:$D$6,4,0) -> North | R3: 4 | S3: 0.1 | T3: Mobile Money | U3: =M3*R3 -> 102.28 | V3: =N3*R3 -> 76.2 | W3: =U3-V3-(1-S3) -> 25.18
A4: T01905 | B4: 45179 | C4: C110 | D4: =VLOOKUP(C4,Customers!$A$1:$H$201,4,0) -> Travis Peters | E4: =VLOOKUP(C4,Customers!$A$1:$H$201,5,0) -> Female | F4: =VLOOKUP(C4,Customers!$A$1:$H$201,6,0) -> 24112 | G4: =VLOOKUP(C4,Customers!$A$1:$H$201,7,0) -> South Ianhaven | H4: =VLOOKUP(C4,Customers!$A$1:$H$201,8,0) -> 44926 | I4: P023 | J4: =VLOOKUP(I4,Products!$A$1:$F$51,2,0) -> And Footwear | K4: =VLOOKUP(I4,Products!$A$1:$F$51,3,0) -> Fashion | L4: =VLOOKUP(I4,Products!$A$1:$F$51,4,0) -> Footwear | M4: =VLOOKUP(I4,Products!$A$1:$F$51,5,0) -> 1878.47 | N4: =VLOOKUP(I4,Products!$A$1:$F$51,6,0) -> 1014.91 | O4: S002 | P4: =VLOOKUP(O4,Stores!$A$1:$D$6,2,0) -> MegaMart Peckmouth | Q4: =VLOOKUP(O4,Stores!$A$1:$D$6,4,0) -> East | R4: 5 | S4: 0.1 | T4: Cash | U4: =M4*R4 -> 9392.35 | V4: =N4*R4 -> 5074.55 | W4: =U4-V4-(1-S4) -> 4316.9
A5: T01936 | B5: 45179 | C5: C151 | D5: =VLOOKUP(C5,Customers!$A$1:$H$201,4,0) -> Dawn Fletcher | E5: =VLOOKUP(C5,Customers!$A$1:$H$201,5,0) -> Male | F5: =VLOOKUP(C5,Customers!$A$1:$H$201,6,0) -> 38959 | G5: =VLOOKUP(C5,Customers!$A$1:$H$201,7,0) -> South Audrey | H5: =VLOOKUP(C5,Customers!$A$1:$H$201,8,0) -> 44587 | I5: P004 | J5: =VLOOKUP(I5,Products!$A$1:$F$51,2,0) -> Four Accessories | K5: =VLOOKUP(I5,Products!$A$1:$F$51,3,0) -> Fashion | L5: =VLOOKUP(I5,Products!$A$1:$F$51,4,0) -> Accessories | M5: =VLOOKUP(I5,Products!$A$1:$F$51,5,0) -> 1853.77 | N5: =VLOOKUP(I5,Products!$A$1:$F$51,6,0) -> 1363.52 | O5: S002 | P5: =VLOOKUP(O5,Stores!$A$1:$D$6,2,0) -> MegaMart Peckmouth | Q5: =VLOOKUP(O5,Stores!$A$1:$D$6,4,0) -> East | R5: 2 | S5: 0.15 | T5: Cash | U5: =M5*R5 -> 3707.54 | V5: =N5*R5 -> 2727.04 | W5: =U5-V5-(1-S5) -> 979.65
A6: T02496 | B6: 45179 | C6: C141 | D6: =VLOOKUP(C6,Customers!$A$1:$H$201,4,0) -> Adam Lucas | E6: =VLOOKUP(C6,Customers!$A$1:$H$201,5,0) -> Female | F6: =VLOOKUP(C6,Customers!$A$1:$H$201,6,0) -> 28708 | G6: =VLOOKUP(C6,Customers!$A$1:$H$201,7,0) -> Allisonmouth | H6: =VLOOKUP(C6,Customers!$A$1:$H$201,8,0) -> 45298 | I6: P040 | J6: =VLOOKUP(I6,Products!$A$1:$F$51,2,0) -> Piece Headphones | K6: =VLOOKUP(I6,Products!$A$1:$F$51,3,0) -> Electronics | L6: =VLOOKUP(I6,Products!$A$1:$F$51,4,0) -> Headphones | M6: =VLOOKUP(I6,Products!$A$1:$F$51,5,0) -> 1745.61 | N6: =VLOOKUP(I6,Products!$A$1:$F$51,6,0) -> 1322.44 | O6: S004 | P6: =VLOOKUP(O6,Stores!$A$1:$D$6,2,0) -> MegaMart Brianahaven | Q6: =VLOOKUP(O6,Stores!$A$1:$D$6,4,0) -> North | R6: 2 | S6: 0.15 | T6: Mobile Money | U6: =M6*R6 -> 3491.22 | V6: =N6*R6 -> 2644.88 | W6: =U6-V6-(1-S6) -> 845.49
A7: T02913 | B7: 45179 | C7: C110 | D7: =VLOOKUP(C7,Customers!$A$1:$H$201,4,0) -> Travis Peters | E7: =VLOOKUP(C7,Customers!$A$1:$H$201,5,0) -> Female | F7: =VLOOKUP(C7,Customers!$A$1:$H$201,6,0) -> 24112 | G7: =VLOOKUP(C7,Customers!$A$1:$H$201,7,0) -> South Ianhaven | H7: =VLOOKUP(C7,Customers!$A$1:$H$201,8,0) -> 44926 | I7: P049 | J7: =VLOOKUP(I7,Products!$A$1:$F$51,2,0) -> Possible Watches | K7: =VLOOKUP(I7,Products!$A$1:$F$51,3,0) -> Fashion | L7: =VLOOKUP(I7,Products!$A$1:$F$51,4,0) -> Watches | M7: =VLOOKUP(I7,Products!$A$1:$F$51,5,0) -> 388.26 | N7: =VLOOKUP(I7,Products!$A$1:$F$51,6,0) -> 199.3 | O7: S003 | P7: =VLOOKUP(O7,Stores!$A$1:$D$6,2,0) -> MegaMart New Michele | Q7: =VLOOKUP(O7,Stores!$A$1:$D$6,4,0) -> West | R7: 3 | S7: 0.05 | T7: Cash | U7: =M7*R7 -> 1164.78 | V7: =N7*R7 -> 597.9 | W7: =U7-V7-(1-S7) -> 565.93
A8: T03472 | B8: 45180 | C8: C101 | D8: =VLOOKUP(C8,Customers!$A$1:$H$201,4,0) -> William Pope | E8: =VLOOKUP(C8,Customers!$A$1:$H$201,5,0) -> Female | F8: =VLOOKUP(C8,Customers!$A$1:$H$201,6,0) -> 20604 | G8: =VLOOKUP(C8,Customers!$A$1:$H$201,7,0) -> North Gary | H8: =VLOOKUP(C8,Customers!$A$1:$H$201,8,0) -> 45543 | I8: P023 | J8: =VLOOKUP(I8,Products!$A$1:$F$51,2,0) -> And Footwear | K8: =VLOOKUP(I8,Products!$A$1:$F$51,3,0) -> Fashion | L8: =VLOOKUP(I8,Products!$A$1:$F$51,4,0) -> Footwear | M8: =VLOOKUP(I8,Products!$A$1:$F$51,5,0) -> 1878.47 | N8: =VLOOKUP(I8,Products!$A$1:$F$51,6,0) -> 1014.91 | O8: S002 | P8: =VLOOKUP(O8,Stores!$A$1:$D$6,2,0) -> MegaMart Peckmouth | Q8: =VLOOKUP(O8,Stores!$A$1:$D$6,4,0) -> East | R8: 1 | S8: 0.15 | T8: Credit Card | U8: =M8*R8 -> 1878.47 | V8: =N8*R8 -> 1014.91 | W8: =U8-V8-(1-S8) -> 862.71
A9: T03734 | B9: 45180 | C9: C193 | D9: =VLOOKUP(C9,Customers!$A$1:$H$201,4,0) -> Donald Meza | E9: =VLOOKUP(C9,Customers!$A$1:$H$201,5,0) -> Female | F9: =VLOOKUP(C9,Customers!$A$1:$H$201,6,0) -> 25513 | G9: =VLOOKUP(C9,Customers!$A$1:$H$201,7,0) -> North Kelly | H9: =VLOOKUP(C9,Customers!$A$1:$H$201,8,0) -> 44173 | I9: P028 | J9: =VLOOKUP(I9,Products!$A$1:$F$51,2,0) -> Deal Smartphone | K9: =VLOOKUP(I9,Products!$A$1:$F$51,3,0) -> Electronics | L9: =VLOOKUP(I9,Products!$A$1:$F$51,4,0) -> Smartphone | M9: =VLOOKUP(I9,Products!$A$1:$F$51,5,0) -> 673.78 | N9: =VLOOKUP(I9,Products!$A$1:$F$51,6,0) -> 363.33 | O9: S003 | P9: =VLOOKUP(O9,Stores!$A$1:$D$6,2,0) -> MegaMart New Michele | Q9: =VLOOKUP(O9,Stores!$A$1:$D$6,4,0) -> West | R9: 4 | S9: 0.05 | T9: Bank Transfer | U9: =M9*R9 -> 2695.12 | V9: =N9*R9 -> 1453.32 | W9: =U9-V9-(1-S9) -> 1240.85
A10: T04210 | B10: 45180 | C10: C012 | D10: =VLOOKUP(C10,Customers!$A$1:$H$201,4,0) -> Dale Perry | E10: =VLOOKUP(C10,Customers!$A$1:$H$201,5,0) -> Male | F10: =VLOOKUP(C10,Customers!$A$1:$H$201,6,0) -> 32850 | G10: =VLOOKUP(C10,Customers!$A$1:$H$201,7,0) -> Lake Dawn | H10: =VLOOKUP(C10,Customers!$A$1:$H$201,8,0) -> 44393 | I10: P036 | J10: =VLOOKUP(I10,Products!$A$1:$F$51,2,0) -> New Watches | K10: =VLOOKUP(I10,Products!$A$1:$F$51,3,0) -> Fashion | L10: =VLOOKUP(I10,Products!$A$1:$F$51,4,0) -> Watches | M10: =VLOOKUP(I10,Products!$A$1:$F$51,5,0) -> 1501.46 | N10: =VLOOKUP(I10,Products!$A$1:$F$51,6,0) -> 1167.73 | O10: S003 | P10: =VLOOKUP(O10,Stores!$A$1:$D$6,2,0) -> MegaMart New Michele | Q10: =VLOOKUP(O10,Stores!$A$1:$D$6,4,0) -> West | R10: 5 | S10: 0.05 | T10: Credit Card | U10: =M10*R10 -> 7507.3 | V10: =N10*R10 -> 5838.65 | W10: =U10-V10-(1-S10) -> 1667.7
A11: T01740 | B11: 45180 | C11: C168 | D11: =VLOOKUP(C11,Customers!$A$1:$H$201,4,0) -> Richard Jones | E11: =VLOOKUP(C11,Customers!$A$1:$H$201,5,0) -> Male | F11: =VLOOKUP(C11,Customers!$A$1:$H$201,6,0) -> 25414 | G11: =VLOOKUP(C11,Customers!$A$1:$H$201,7,0) -> Lake Steventown | H11: =VLOOKUP(C11,Customers!$A$1:$H$201,8,0) -> 44835 | I11: P050 | J11: =VLOOKUP(I11,Products!$A$1:$F$51,2,0) -> Maybe Footwear | K11: =VLOOKUP(I11,Products!$A$1:$F$51,3,0) -> Fashion | L11: =VLOOKUP(I11,Products!$A$1:$F$51,4,0) -> Footwear | M11: =VLOOKUP(I11,Products!$A$1:$F$51,5,0) -> 1044.64 | N11: =VLOOKUP(I11,Products!$A$1:$F$51,6,0) -> 775.07 | O11: S003 | P11: =VLOOKUP(O11,Stores!$A$1:$D$6,2,0) -> MegaMart New Michele | Q11: =VLOOKUP(O11,Stores!$A$1:$D$6,4,0) -> West | R11: 1 | S11: 0.15 | T11: Credit Card | U11: =M11*R11 -> 1044.64 | V11: =N11*R11 -> 775.07 | W11: =U11-V11-(1-S11) -> 268.72
A12: T03098 | B12: 45181 | C12: C036 | D12: =VLOOKUP(C12,Customers!$A$1:$H$201,4,0) -> Michael Cervantes | E12: =VLOOKUP(C12,Customers!$A$1:$H$201,5,0) -> Male | F12: =VLOOKUP(C12,Customers!$A$1:$H$201,6,0) -> 33546 | G12: =VLOOKUP(C12,Customers!$A$1:$H$201,7,0) -> Ashleyview | H12: =VLOOKUP(C12,Customers!$A$1:$H$201,8,0) -> 44104 | I12: P040 | J12: =VLOOKUP(I12,Products!$A$1:$F$51,2,0) -> Piece Headphones | K12: =VLOOKUP(I12,Products!$A$1:$F$51,3,0) -> Electronics | L12: =VLOOKUP(I12,Products!$A$1:$F$51,4,0) -> Headphones | M12: =VLOOKUP(I12,Products!$A$1:$F$51,5,0) -> 1745.61 | N12: =VLOOKUP(I12,Products!$A$1:$F$51,6,0) -> 1322.44 | O12: S002 | P12: =VLOOKUP(O12,Stores!$A$1:$D$6,2,0) -> MegaMart Peckmouth | Q12: =VLOOKUP(O12,Stores!$A$1:$D$6,4,0) -> East | R12: 1 | S12: 0.1 | T12: Cash | U12: =M12*R12 -> 1745.61 | V12: =N12*R12 -> 1322.44 | W12: =U12-V12-(1-S12) -> 422.27
A13: T03785 | B13: 45181 | C13: C132 | D13: =VLOOKUP(C13,Customers!$A$1:$H$201,4,0) -> Jared Ochoa | E13: =VLOOKUP(C13,Customers!$A$1:$H$201,5,0) -> Male | F13: =VLOOKUP(C13,Customers!$A$1:$H$201,6,0) -> 21543 | G13: =VLOOKUP(C13,Customers!$A$1:$H$201,7,0) -> Cisnerosville | H13: =VLOOKUP(C13,Customers!$A$1:$H$201,8,0) -> 45035 | I13: P022 | J13: =VLOOKUP(I13,Products!$A$1:$F$51,2,0) -> How Vegetables | K13: =VLOOKUP(I13,Products!$A$1:$F$51,3,0) -> Groceries | L13: =VLOOKUP(I13,Products!$A$1:$F$51,4,0) -> Vegetables | M13: =VLOOKUP(I13,Products!$A$1:$F$51,5,0) -> 25.57 | N13: =VLOOKUP(I13,Products!$A$1:$F$51,6,0) -> 19.05 | O13: S002 | P13: =VLOOKUP(O13,Stores!$A$1:$D$6,2,0) -> MegaMart Peckmouth | Q13: =VLOOKUP(O13,Stores!$A$1:$D$6,4,0) -> East | R13: 3 | S13: 0.05 | T13: Cash | U13: =M13*R13 -> 76.71 | V13: =N13*R13 -> 57.15 | W13: =U13-V13-(1-S13) -> 18.61
... A5001: T04034 | B5001: 45909 | C5001: C166 | D5001: =VLOOKUP(C5001,Customers!$A$1:$H$201,4,0) -> Meagan Ali | E5001: =VLOOKUP(C5001,Customers!$A$1:$H$201,5,0) -> Female | F5001: =VLOOKUP(C5001,Customers!$A$1:$H$201,6,0) -> 37024 | G5001: =VLOOKUP(C5001,Customers!$A$1:$H$201,7,0) -> South Markbury | H5001: =VLOOKUP(C5001,Customers!$A$1:$H$201,8,0) -> 45117 | I5001: P034 | J5001: =VLOOKUP(I5001,Products!$A$1:$F$51,2,0) -> Everything Laptop | K5001: =VLOOKUP(I5001,Products!$A$1:$F$51,3,0) -> Electronics | L5001: =VLOOKUP(I5001,Products!$A$1:$F$51,4,0) -> Laptop | M5001: =VLOOKUP(I5001,Products!$A$1:$F$51,5,0) -> 428.05 | N5001: =VLOOKUP(I5001,Products!$A$1:$F$51,6,0) -> 246.07 | O5001: S001 | P5001: =VLOOKUP(O5001,Stores!$A$1:$D$6,2,0) -> MegaMart Jimenezborough | Q5001: =VLOOKUP(O5001,Stores!$A$1:$D$6,4,0) -> South | R5001: 3 | S5001: 0.05 | T5001: Mobile Money | U5001: =M5001*R5001 -> 1284.15 | V5001: =N5001*R5001 -> 738.21 | W5001: =U5001-V5001-(1-S5001) -> 544.99

Sheet Descriptive Statistics
A1: Unite_Price | B1: Cost_Price | C1: Quantity | D1: Discount
A2: 1246.11 | B2: 833.52 | C2: 4 | D2: 0.15 | G2: Unite_Price | I2: Cost_Price | K2: Quantity | M2: Discount
A3: 25.57 | B3: 19.05 | C3: 4 | D3: 0.1
A4: 1878.47 | B4: 1014.91 | C4: 5 | D4: 0.1 | G4: Mean | H4: 1105.9509 | I4: Mean | J4: 747.42526 | K4: Mean | L4: 2.9905585 | M4: Mean | N4: 0.075826488
A5: 1853.77 | B5: 1363.52 | C5: 2 | D5: 0.15 | G5: Standard Error | H5: 7.7420153 | I5: Standard Error | J5: 5.5983903 | K5: Standard Error | L5: 0.019878161 | M5: Standard Error | N5: 0.00079835212
A6: 1745.61 | B6: 1322.44 | C6: 2 | D6: 0.15 | G6: Median | H6: 1193.09 | I6: Median | J6: 794.8 | K6: Median | L6: 3 | M6: Median | N6: 0.1
A7: 388.26 | B7: 199.3 | C7: 3 | D7: 0.05 | G7: Mode | H7: 1102.7918 | I7: Mode | J7: 742.26522 | K7: Mode | L7: 2 | M7: Mode | N7: 0.15
A8: 1878.47 | B8: 1014.91 | C8: 1 | D8: 0.15 | G8: Standard Deviation | H8: 547.44315 | I8: Standard Deviation | J8: 395.86597 | K8: Standard Deviation | L8: 1.4055982 | M8: Standard Deviation | N8: 0.05645202
A9: 673.78 | B9: 363.33 | C9: 4 | D9: 0.05 | G9: Sample Variance | H9: 299694 | I9: Sample Variance | J9: 156709.87 | K9: Sample Variance | L9: 1.9757064 | M9: Sample Variance | N9: 0.0031868305
A10: 1501.46 | B10: 1167.73 | C10: 5 | D10: 0.05 | G10: Kurtosis | H10: -0.77219245 | I10: Kurtosis | J10: -0.86401855 | K10: Kurtosis | L10: -1.2845008 | M10: Kurtosis | N10: -1.3846195
A11: 1044.64 | B11: 775.07 | C11: 1 | D11: 0.15 | G11: Skewness | H11: -0.43256414 | I11: Skewness | J11: -0.10009025 | K11: Skewness | L11: 0.011584272 | M11: Skewness | N11: -0.0089545641
A12: 1745.61 | B12: 1322.44 | C12: 1 | D12: 0.1 | G12: Range | H12: 1927.08 | I12: Range | J12: 1432.22 | K12: Range | L12: 4 | M12: Range | N12: 0.15
A13: 25.57 | B13: 19.05 | C13: 3 | D13: 0.05 | G13: Minimum | H13: 25.57 | I13: Minimum | J13: 19.05 | K13: Minimum | L13: 1 | M13: Minimum | N13: 0
A14: 1272.23 | B14: 952.65 | C14: 5 | D14: 0.15 | G14: Maximum | H14: 1952.65 | I14: Maximum | J14: 1451.27 | K14: Maximum | L14: 5 | M14: Maximum | N14: 0.15
A15: 1079.89 | B15: 703.83 | C15: 5 | D15: 0.15 | G15: Sum | H15: 5529754.4 | I15: Sum | J15: 3737126.3 | K15: Sum | L15: 14952.792 | M15: Sum | N15: 379.13244
A16: 29.24 | B16: 742.26522 | C16: 3 | D16: 0.15 | G16: Count | H16: 5000 | I16: Count | J16: 5000 | K16: Count | L16: 5000 | M16: Count | N16: 5000
A17: 1745.61 | B17: 1322.44 | C17: 2 | D17: 0
A18: 1102.7918 | B18: 169.03 | C18: 2 | D18: 0.1
A19: 248.57 | B19: 190.67 | C19: 1 | D19: 0
A20: 1485.05 | B20: 988.31 | C20: 4 | D20: 0.05
A21: 1396.22 | B21: 1004.09 | C21: 3 | D21: 0
A22: 25.57 | B22: 19.05 | C22: 2 | D22: 0.15
A23: 1216.36 | B23: 794.8 | C23: 5 | D23: 0
A24: 1272.23 | B24: 952.65 | C24: 5 | D24: 0.1
A25: 1079.89 | B25: 703.83 | C25: 4 | D25: 0
A26: 1165.37 | B26: 926.55 | C26: 2 | D26: 0
A27: 1879.08 | B27: 1004.56 | C27: 2 | D27: 0.1
A28: 1762.92 | B28: 1346.48 | C28: 2 | D28: 0.15
... A5001: 428.05 | B5001: 246.07 | C5001: 3 | D5001: 0.05
